text_morse_code_converter/__init__.py
text_morse_code_converter/__main__.py
text_morse_code_converter/file_converter.py
text_morse_code_converter/message_generator.py
text_morse_code_converter/morse_code_converter.py
text_morse_code_converter-0.1.2.dist-info/licenses/LICENSE
text_morse_code_converter-0.1.2.dist-info/METADATA
text_morse_code_converter-0.1.2.dist-info/WHEEL
text_morse_code_converter-0.1.2.dist-info/top_level.txt
text_morse_code_converter-0.1.2.dist-info/RECORD
