Metadata-Version: 2.4
Name: text-morse-code-converter
Version: 0.1.2
Summary: A simple Morse code converter
Home-page: https://github.com/orgs/software-students-spring2025/teams/bytebusters
Author: ByteBusters Team
License:                     GNU GENERAL PUBLIC LICENSE
Classifier: Programming Language :: Python :: 3
Classifier: License :: OSI Approved :: MIT License
Classifier: Operating System :: OS Independent
Requires-Python: >=3.6
License-File: LICENSE
Requires-Dist: sounddevice>=0.4.6
Requires-Dist: numpy>=2.2.4
Provides-Extra: dev
Requires-Dist: pytest; extra == "dev"
Requires-Dist: ruff; extra == "dev"
Dynamic: home-page
Dynamic: license-file
Dynamic: requires-python
